sumoappclient/__init__.py
sumoappclient/console.py
sumoappclient/common/__init__.py
sumoappclient/common/ctocstatus.py
sumoappclient/common/errors.py
sumoappclient/common/logger.py
sumoappclient/common/mixin.py
sumoappclient/common/utils.py
sumoappclient/configmanager/__init__.py
sumoappclient/configmanager/aws.py
sumoappclient/configmanager/azure.py
sumoappclient/configmanager/base.py
sumoappclient/configmanager/ctoc.py
sumoappclient/configmanager/gcp.py
sumoappclient/configmanager/onprem.py
sumoappclient/omnistorage/__init__.py
sumoappclient/omnistorage/aws.py
sumoappclient/omnistorage/azure.py
sumoappclient/omnistorage/base.py
sumoappclient/omnistorage/ctoc.py
sumoappclient/omnistorage/gcp.py
sumoappclient/omnistorage/onprem.py
sumoappclient/pkggenerator/__init__.py
sumoappclient/pkggenerator/aws.py
sumoappclient/pkggenerator/base.py
sumoappclient/pkggenerator/onprem.py
sumoappclient/pkggenerator/setupgen.py
sumoappclient/pkggenerator/utils.py
sumoappclient/pkggenerator/resources/aws/basesamtemplate.yaml
sumoappclient/pkggenerator/resources/aws/basesamwithkms.yaml
sumoappclient/pkggenerator/resources/setup/LICENSE
sumoappclient/pkggenerator/resources/setup/MANIFEST.in
sumoappclient/pkggenerator/resources/setup/README.md
sumoappclient/pkggenerator/resources/setup/VERSION
sumoappclient/pkggenerator/resources/setup/baseconfig.yaml
sumoappclient/pkggenerator/resources/setup/setup.py
sumoappclient/provider/__init__.py
sumoappclient/provider/aws.py
sumoappclient/provider/azure.py
sumoappclient/provider/base.py
sumoappclient/provider/ctoc.py
sumoappclient/provider/factory.py
sumoappclient/provider/gcp.py
sumoappclient/provider/onprem.py
sumoappclient/sumoclient/__init__.py
sumoappclient/sumoclient/base.py
sumoappclient/sumoclient/factory.py
sumoappclient/sumoclient/httputils.py
sumoappclient/sumoclient/outputhandlers.py
sumoappclient/sumoclient/utils.py
tests/__init__.py
tests/base.py
tests/test_config.py
tests/test_provider.py
tests/test_storage.py
sumologic_appclient_sdk-2.0.10.dist-info/LICENSE
sumologic_appclient_sdk-2.0.10.dist-info/METADATA
sumologic_appclient_sdk-2.0.10.dist-info/WHEEL
sumologic_appclient_sdk-2.0.10.dist-info/entry_points.txt
sumologic_appclient_sdk-2.0.10.dist-info/top_level.txt
sumologic_appclient_sdk-2.0.10.dist-info/zip-safe
sumologic_appclient_sdk-2.0.10.dist-info/RECORD
